cellxgene_schema/__init__.py
cellxgene_schema/atac_seq.py
cellxgene_schema/cli.py
cellxgene_schema/env.py
cellxgene_schema/gencode.py
cellxgene_schema/map_species.py
cellxgene_schema/matrix_utils.py
cellxgene_schema/migrate.py
cellxgene_schema/ontology_parser.py
cellxgene_schema/remove_labels.py
cellxgene_schema/schema.py
cellxgene_schema/utils.py
cellxgene_schema/validate.py
cellxgene_schema/write_labels.py
cellxgene_schema/gencode_files/genes_caenorhabditis_elegans.csv.gz
cellxgene_schema/gencode_files/genes_callithrix_jacchus.csv.gz
cellxgene_schema/gencode_files/genes_danio_rerio.csv.gz
cellxgene_schema/gencode_files/genes_drosophila_melanogaster.csv.gz
cellxgene_schema/gencode_files/genes_ercc.csv.gz
cellxgene_schema/gencode_files/genes_gorilla_gorilla.csv.gz
cellxgene_schema/gencode_files/genes_homo_sapiens.csv.gz
cellxgene_schema/gencode_files/genes_macaca_fascicularis.csv.gz
cellxgene_schema/gencode_files/genes_macaca_mulatta.csv.gz
cellxgene_schema/gencode_files/genes_microcebus_murinus.csv.gz
cellxgene_schema/gencode_files/genes_mus_musculus.csv.gz
cellxgene_schema/gencode_files/genes_oryctolagus_cuniculus.csv.gz
cellxgene_schema/gencode_files/genes_pan_troglodytes.csv.gz
cellxgene_schema/gencode_files/genes_rattus_norvegicus.csv.gz
cellxgene_schema/gencode_files/genes_sars_cov_2.csv.gz
cellxgene_schema/gencode_files/genes_sus_scrofa.csv.gz
cellxgene_schema/migrate_files/automigrate_terms.json
cellxgene_schema/migrate_files/donor_updates.json
cellxgene_schema/migrate_files/non_csr_list.txt
cellxgene_schema/migrate_files/private_non_csr.json
cellxgene_schema/migrate_files/schema7_hancestro_mapping.json
cellxgene_schema/migrate_files/title_donor_updates.json
cellxgene_schema/schema_definitions/schema_definition.yaml
cellxgene_schema/validation_internals/__init__.py
cellxgene_schema/validation_internals/check_duplicates.py
cellxgene_schema-7.0.1.dist-info/LICENSE.md
cellxgene_schema-7.0.1.dist-info/METADATA
cellxgene_schema-7.0.1.dist-info/WHEEL
cellxgene_schema-7.0.1.dist-info/entry_points.txt
cellxgene_schema-7.0.1.dist-info/top_level.txt
cellxgene_schema-7.0.1.dist-info/RECORD
