Metadata-Version: 2.1
Name: cellxgene-schema
Version: 7.0.1
Summary: Tool for applying and validating cellxgene integration schema to single cell datasets
Home-page: https://github.com/chanzuckerberg/single-cell-curation
Author: Chan Zuckerberg Initiative
Author-email: cellxgene@chanzuckerberg.com
License: MIT
Classifier: Intended Audience :: Science/Research
Classifier: License :: OSI Approved :: MIT License
Classifier: Natural Language :: English
Classifier: Programming Language :: Python :: 3
Classifier: Topic :: Scientific/Engineering :: Bio-Informatics
Requires-Python: >=3.10
License-File: LICENSE.md
Requires-Dist: anndata ==0.11.4
Requires-Dist: cellxgene-ontology-guide ==1.9.0
Requires-Dist: click <9
Requires-Dist: Cython <4
Requires-Dist: dask[array,dataframe] ==2024.12.0
Requires-Dist: duckdb ==1.3.2
Requires-Dist: ibis-framework[duckdb] >=10.3
Requires-Dist: numpy <3
Requires-Dist: pandas <3,>2
Requires-Dist: pyarrow >=19
Requires-Dist: PyYAML <7
Requires-Dist: scipy <1.16
Requires-Dist: sparse ==0.15.1
Requires-Dist: semver <4
Requires-Dist: xxhash <4
Requires-Dist: matplotlib <4
Requires-Dist: pysam >=0.13.0
